{
  "generated_at_utc": "2025-10-20T01:53:36.432Z",
  "generated_at_local": "2025-10-20T02:53:36",
  "source": "flightradar24.com (screen-scrape)",
  "horizon_minutes": 180,
  "rows": [
    {
      "flight": "BY6765",
      "origin": "(LCA)",
      "origin_iata": "LCA",
      "eta": "2025-10-20T03:14:00.000Z",
      "status": "estimated 04:14",
      "flow": "INTERNATIONAL",
      "belt": 1,
      "start": "2025-10-20T03:29:00.000Z",
      "end": "2025-10-20T03:59:00.000Z",
      "reason": "intl_spread",
      "airline": "TUI",
      "aircraft": "(G-TUMG)",
      "pax_estimate": 166,
      "scheduled_local": "04:20",
      "eta_local": "04:14",
      "delay_min": -6,
      "ui_state": "upcoming",
      "ui_age_min": -125
    }
  ]
}