{
  "generated_at_utc": "2025-10-20T19:23:35.177Z",
  "generated_at_local": "2025-10-20T20:23:35",
  "source": "flightradar24.com (screen-scrape)",
  "horizon_minutes": 180,
  "rows": [
    {
      "flight": "U2319",
      "origin": "(EDI)",
      "origin_iata": "EDI",
      "eta": "2025-10-20T19:56:00.000Z",
      "status": "delayed 20:56",
      "flow": "DOMESTIC",
      "belt": 7,
      "start": "2025-10-20T20:11:00.000Z",
      "end": "2025-10-20T20:41:00.000Z",
      "reason": "domestic→7",
      "airline": "easyJet",
      "aircraft": "(G-EZRX)",
      "pax_estimate": 162,
      "scheduled_local": "20:40",
      "eta_local": "20:56",
      "delay_min": 16
    },
    {
      "flight": "FR506",
      "origin": "(DUB)",
      "origin_iata": "DUB",
      "eta": "2025-10-20T19:56:00.000Z",
      "status": "estimated 20:56",
      "flow": "CTA",
      "belt": 6,
      "start": "2025-10-20T20:11:00.000Z",
      "end": "2025-10-20T20:41:00.000Z",
      "reason": "cta→6",
      "airline": "Ryanair",
      "aircraft": "(9H-QCP)",
      "pax_estimate": 166,
      "scheduled_local": "21:05",
      "eta_local": "20:56",
      "delay_min": -9
    },
    {
      "flight": "FR8235",
      "origin": "(PMI)",
      "origin_iata": "PMI",
      "eta": "2025-10-20T21:20:00.000Z",
      "status": "estimated 22:20",
      "flow": "INTERNATIONAL",
      "belt": 1,
      "start": "2025-10-20T21:35:00.000Z",
      "end": "2025-10-20T22:05:00.000Z",
      "reason": "intl_spread",
      "airline": "Buzz",
      "aircraft": "(SP-RZG)",
      "pax_estimate": 166,
      "scheduled_local": "22:40",
      "eta_local": "22:20",
      "delay_min": -20
    },
    {
      "flight": "LS1814",
      "origin": "(BJV)",
      "origin_iata": "BJV",
      "eta": "2025-10-20T22:00:00.000Z",
      "status": "estimated 23:00",
      "flow": "INTERNATIONAL",
      "belt": 2,
      "start": "2025-10-20T22:15:00.000Z",
      "end": "2025-10-20T22:45:00.000Z",
      "reason": "intl_spread",
      "airline": "Jet2",
      "aircraft": "(G-JZBW)",
      "pax_estimate": 176,
      "scheduled_local": "23:10",
      "eta_local": "23:00",
      "delay_min": -10
    }
  ]
}